MANIFEST.in
README.md
make.sh
setup.py
zwatershed/__init__.py
zwatershed/edgelist_methods.py
zwatershed/par_funcs.py
zwatershed/run_tests.py
zwatershed/setup.py
zwatershed/zwatershed.h
zwatershed/zwatershed.pyx
zwatershed/zwatershed_main.cpp
zwatershed.egg-info/PKG-INFO
zwatershed.egg-info/SOURCES.txt
zwatershed.egg-info/dependency_links.txt
zwatershed.egg-info/not-zip-safe
zwatershed.egg-info/pbr.json
zwatershed.egg-info/requires.txt
zwatershed.egg-info/top_level.txt
zwatershed/zi/bits/array.hpp
zwatershed/zi/bits/bind.hpp
zwatershed/zi/bits/cerrno.hpp
zwatershed/zi/bits/complex.hpp
zwatershed/zi/bits/cstdint.hpp
zwatershed/zi/bits/enable_shared_from_this.hpp
zwatershed/zi/bits/function.hpp
zwatershed/zi/bits/hash.hpp
zwatershed/zi/bits/mem_fn.hpp
zwatershed/zi/bits/random.hpp
zwatershed/zi/bits/ref.hpp
zwatershed/zi/bits/result_of.hpp
zwatershed/zi/bits/shared_ptr.hpp
zwatershed/zi/bits/slist.hpp
zwatershed/zi/bits/tuple.hpp
zwatershed/zi/bits/type_traits.hpp
zwatershed/zi/bits/typeof.hpp
zwatershed/zi/bits/unordered_map.hpp
zwatershed/zi/bits/unordered_set.hpp
zwatershed/zi/config/config.hpp
zwatershed/zi/config/posix.hpp
zwatershed/zi/config/compiler/gcc.hpp
zwatershed/zi/config/compiler/msvc.hpp
zwatershed/zi/config/os/linux.hpp
zwatershed/zi/config/os/macos.hpp
zwatershed/zi/config/os/windows.hpp
zwatershed/zi/disjoint_sets/disjoint_sets.hpp
zwatershed/zi/disjoint_sets/disjoint_sets2.hpp
zwatershed/zi/disjoint_sets/disjoint_sets_tmp.hpp
zwatershed/zi/utility/address_of.hpp
zwatershed/zi/utility/assert.hpp
zwatershed/zi/utility/binary_printer.hpp
zwatershed/zi/utility/container_utilities.hpp
zwatershed/zi/utility/deferred_instantiation.hpp
zwatershed/zi/utility/enable_if.hpp
zwatershed/zi/utility/enable_singleton_of_this.hpp
zwatershed/zi/utility/exception.hpp
zwatershed/zi/utility/for_each.hpp
zwatershed/zi/utility/is_complex.hpp
zwatershed/zi/utility/is_printable.hpp
zwatershed/zi/utility/natural_compare.hpp
zwatershed/zi/utility/non_copyable.hpp
zwatershed/zi/utility/singleton.hpp
zwatershed/zi/utility/static_and.hpp
zwatershed/zi/utility/static_assert.hpp
zwatershed/zi/utility/static_if.hpp
zwatershed/zi/utility/static_or.hpp
zwatershed/zi/utility/string_printf.hpp
