Metadata-Version: 1.0
Name: zwatershed
Version: 0.9
Summary: Fast watersheds
Home-page: https://github.com/TuragaLab/zwatershed
Author: Chandan Singh
Author-email: csinva@virginia.edu
License: MIT
Platform: UNKNOWN
